<?xml version="1.0"?>
<page xmlns:xsi="http://www.w3.org/2001/XMLSchema-instance" layout="2columns-left" xsi:noNamespaceSchemaLocation="urn:magento:framework:View/Layout/etc/page_configuration.xsd" label="Customer My Account (All Pages)" design_abstraction="custom">
    <head>
        <css src="Cmsmart_Marketplace::css/productdetails.css"/>
        <css src="Cmsmart_Marketplace::css/font-awesome.css"/>
    </head>
    <body>
        <referenceContainer name="content">
            <block class="Cmsmart\Marketplace\Block\Catalog\Product\View" name="product.info.linktoshop" after="product.info.media" template="Cmsmart_Marketplace::catalog/product/link.phtml" cacheable="false">
            </block>
        </referenceContainer>
        <referenceContainer name="product.info.form.content">
            <block class="Cmsmart\Marketplace\Block\Catalog\Product\View" name="product.info.addtocart" as="addtocart" template="Cmsmart_Marketplace::catalog/product/vacation-to-cart.phtml"/>
        </referenceContainer>
        <referenceBlock name="product.info.options.wrapper.bottom">
            <block class="Cmsmart\Marketplace\Block\Catalog\Product\View" name="product.info.addtocart.additional" template="Cmsmart_Marketplace::catalog/product/vacation-to-cart.phtml" after="-"/>
        </referenceBlock>
    </body>
</page>